{
    "主管機關": "台中市",
    "公告日期": "20251110",
    "處分日期": "20251014",
    "處分字號": "府授勞檢字第1140308102號",
    "事業單位名稱或負責人": "德元結構鋼材有限公司(林進耀)",
    "違法法規法條": "營造安全衛生設施標準第59條第1項第1款暨職業安全衛生法第6條第1項;營造安全衛生設施標準第59條第1項第3款暨職業安全衛生法第6條第1項;營造安全衛生設施標準第41條第1項暨職業安全衛生法第6條第1項;營造安全衛生設施標準第42條第1項第4款暨職業安全衛生法第6條第1項",
    "違反法規內容": "使用國家標準CNS4750型式之施工架，應符合國家標準同等以上之規定；其他型式之施工架，其構材之材料抗拉強度、試驗強度及製造，應符合國家標準CNS4750同等以上之規定。;裝有腳輪之移動式施工架，勞工作業時，其腳部應以有效方法固定之；勞工於其上作業時，不得移動施工架。;雇主對於懸吊式施工架、懸臂式施工架及高度五公尺以上施工架之組配及拆除(以下簡稱施工架組配)作業，應指派施工架組配作業主管於作業現場辦理下列事項：一、決定作業方法，指揮勞工作業。二、實施檢點，檢查材料、工具、器具等，並汰換其不良品。三、監督勞工確實使用個人防護具。四、確認安全衛生設備及措施之有效狀況。五、前二款未確認前，應管制勞工或其他人員不得進入作業。六、其他為維持作業勞工安全衛生所必要之設備及措施。;使勞工從事施工架組配作業，於紮緊、拆卸及傳遞施工架構材等之作業時，設寬度在二十公分以上之施工架踏板，並採取使勞工使用安全帶等防止發生勞工墜落危險之設備與措施。",
    "罰鍰金額": "",
    "備註說明": ""
}