{
    "主管機關": "職業安全衛生署",
    "公告日期": "20210401",
    "處分日期": "20210112",
    "處分字號": "勞職授字第1100200037號",
    "事業單位名稱或負責人": "鄭宇翔即勝翔工程行",
    "違法法規法條": "職業安全衛生設施規則第230條第1項第3、4款營造安全衛生設施標準第133條第1項營造安全衛生設施標準第11條之1暨職業安全衛生法第6條第1項",
    "違反法規內容": "對於使用之合梯，梯腳與地面之角度未在75度以內，且兩梯腳間未有金屬等硬質繫材扣牢，腳部未有防滑絕緣腳座套及未有安全之防滑梯面；對於模板支撐組配、拆除作業，未指派模板支撐作業主管於作業現場辦理下列事項：一、決定作業方法，指揮勞工作業。二、實施檢點，檢查材料、工具、器具等，並汰換其不良品。三、監督勞工確實使用個人防護具。四、確認安全衛生設備及措施之有效狀況。五、其他為維持作業勞工安全衛生所必要之措施；對於進入營繕工程工作場所作業人員，未提供適當安全帽，並使其正確戴用",
    "罰鍰金額": "",
    "備註說明": ""
}