{
    "主管機關": "職業安全衛生署",
    "公告日期": "20190910",
    "處分日期": "20190611",
    "處分字號": "勞職授字第1080202166號",
    "事業單位名稱或負責人": "偉邦營造股份有限公司",
    "違法法規法條": "職業安全衛生設施規則第228條;營造安全衛生設施標準第19條第1項、第20條、第40條第1項、第45條暨職業安全衛生法第6條第1項",
    "違反法規內容": "對於消防通道高差超過1.5公尺以上之外牆施工架場所作業時,未設置使勞工安全上下之設備;對於消防通道設置之電氣機具之帶電部分,未設防止感電之護圍或絕緣被覆;對於高度2公尺以上之消防通道及消防通道外牆施工架工作台開口部分等場所作業,勞工有遭受墜落危險之虞者,未於該處設置護欄或安全網等防護設備;對於護欄前方2公尺內之樓板、地板,堆放物料、設備;對於消防通道高度5公尺以上之外牆施工架,未事先就預期施工時之最大荷重,依結構力學原理妥為設計,未置備施工圖說,並未指派所僱之專任工程人員簽章確認強度計算書、施工圖說及未建立按施工圖說施作之查驗機制,未以斜撐材作適當而充分之支撐,未於適當之垂直、水平距離處未與構造物妥實連接。",
    "罰鍰金額": "",
    "備註說明": ""
}