{
    "主管機關": "台北市",
    "公告日期": "20160318",
    "處分日期": "20160107",
    "處分字號": "北市勞職字第10437032600號",
    "事業單位名稱或負責人": "昕禹實業有限公司",
    "違法法規法條": "1.職業安全衛生法第26條第1項。;2.職業安全衛生法第27條第1項第1、2、3、4款。;3.職業安全衛生設施規則第225條第1項暨職業安全衛生法第6條第1項第5款。",
    "違反法規內容": "1.未於事前告知承攬人有關其泥作工程之工作環境、危害因素暨有關安全衛生規定應採取之措施。;2.與承攬人分別僱用勞工共同作業，對於承攬人所僱勞工於具有墜落危險之調壓池圍堰頂部上從事搬運水泥砂漿作業，勞工有墜落之虞者，未依規定設協議組織，並將承攬人納入協議組織運作，且未「確實巡視」並「指揮」命令停止該危險作業，並未指導及協助安全衛生教育，致發生承攬人所僱勞工墜落致死職業災害。;3.僱用勞工於高度在2公尺以上之處所進行作業，未以架設施工架或其他方法設置工作台，使勞工有遭受墜落危險之虞。",
    "罰鍰金額": "",
    "備註說明": ""
}