{
    "主管機關": "桃園市",
    "公告日期": "20200507",
    "處分日期": "20200326",
    "處分字號": "府勞檢字第1090071229號",
    "事業單位名稱或負責人": "前衛營造有限公司(韓素梅)",
    "違法法規法條": "職業安全衛生設施規則第155條之1第9款暨職業安全衛生法第6條第1項;營造安全衛生設施標準第19條第1項暨職業安全衛生法第6條第1項;營造安全衛生設施標準第51條第2款暨職業安全衛生法第6條第1項;營造安全衛生設施標準第59條第1款暨職業安全衛生法第6條第1項",
    "違反法規內容": "雇主使勞工以捲揚機等吊運物料時，應依下列規定辦理：一、…。九、應設有防止過捲裝置，設置有困難者，得以標示代替之。十、…。;雇主對於高度二公尺以上之屋頂、鋼樑、開口部分、階梯、樓梯、坡道、工作臺、擋土牆、擋土支撐、施工構臺、橋樑墩柱及橋樑上部結構、橋臺等場所作業，勞工有遭受墜落危險之虞者，應於該處設置護欄、護蓋或安全網等防護設備。;雇主於施工架上設置人員上下設備時，應依下列規定辦理：一、…。二、施工架任一處步行至最近上下設備之距離，應在三十公尺以下。;雇主對於鋼管施工架之設置，應依下列規定辦理：一、使用國家標準CNS4750型式之施工架，應符合國家標準同等以上之規定；其他型式之施工架，其構材之材料抗拉強度、試驗強度及製造，應符合國家標準CNS4750同等以上之規定。二、…。",
    "罰鍰金額": "",
    "備註說明": ""
}