{
    "主管機關": "桃園市",
    "公告日期": "20260508",
    "處分日期": "20260323",
    "處分字號": "府勞檢字第1150070866號",
    "事業單位名稱或負責人": "豐景順營造有限公司(曾國慶)",
    "違法法規法條": "職業安全衛生設施規則第243條第1款暨職業安全衛生法第6條第1項;營造安全衛生設施標準第20條第1款暨職業安全衛生法第6條第1項;營造安全衛生設施標準第59條第1項第4款暨職業安全衛生法第6條第1項",
    "違反法規內容": "雇主為避免漏電而發生感電危害，應依下列狀況，於各該電動機具設備之連接電路上設置適合其規格，具有高敏感度、高速型，能確實動作之防止感電用漏電斷路器：使用對地電壓在一百五十伏特以上移動式或攜帶式電動機具。;依規定設置之護欄，應具有高度九十公分以上之上欄杆、中間欄杆或等效設備(以下簡稱中欄杆)、腳趾板及杆柱等構材；其上欄杆、中欄杆及地盤面與樓板面間之上下開口距離，應不大於五十五公分。;構件之連接部分或交叉部分，應以適當之金屬附屬配件確實連接固定，並以適當之斜撐材補強。",
    "罰鍰金額": "100000",
    "備註說明": ""
}