{
    "主管機關": "桃園市",
    "公告日期": "20240207",
    "處分日期": "20231229",
    "處分字號": "府勞檢字第1120370057號",
    "事業單位名稱或負責人": "丞泰開發有限公司(賴清原)",
    "違法法規法條": "機械設備器具安全標準第95條暨職業安全衛生法第6條第1項;機械設備器具安全標準第4條第1項暨職業安全衛生法第6條第1項;機械設備器具安全標準第16條第1款暨職業安全衛生法第6條第1項",
    "違反法規內容": "研磨機之研磨輪，應設置護罩，並具有第九十六條至第一百零四條所定之性能但依國家標準CNS16089附錄A設置安全防護裝置者，不在此限。;以動力驅動之衝壓機械及剪斷機械(以下簡稱衝剪機械)，應具有安全護圍、安全模、特定用途之專用衝剪機械或自動衝剪機械(以下簡稱安全護圍等)但具有防止滑塊等引起危害之機構者，不在此限。;衝剪機械具有下列切換開關之一者，在任何切換狀態，均應有符合第四條所定之安全機能：一、具有連續行程、一行程、安全一行程或寸動行程等之行程切換開關二、…。",
    "罰鍰金額": "",
    "備註說明": ""
}