{
    "主管機關": "桃園市",
    "公告日期": "20240710",
    "處分日期": "20240524",
    "處分字號": "113年府勞檢字第1130141515號",
    "事業單位名稱或負責人": "領航工程有限公司(王青山)",
    "違法法規法條": "營造安全衛生設施標準第6條第1項暨職業安全衛生法第6條第1項；營造安全衛生設施標準第11條之1暨職業安全衛生法第6條第1項；營造安全衛生設施標準第17條暨職業安全衛生法第6條第1項；營造安全衛生設施標準第18條第1項第3款暨職業安全衛生法第6條第1項；營造安全衛生設施標準第18條第2項暨職業安全衛生法第6條第1項；營造安全衛生設施標準第19條第1項暨職業安全衛生法第6條第1項",
    "違反法規內容": "雇主使勞工於營造工程工作場所作業前，應指派所僱之職業安全衛生人員或專任工程人員等專業人員，實施危害調查、評估，並採適當防護設施，以防止職業災害之發生。；雇主對於進入營繕工程工作場所作業人員，應提供適當安全帽，並使其正確戴用。；雇主對於高度二公尺以上之工作場所，勞工作業有墜落之虞者，應訂定墜落災害防止計畫，依下列風險控制之先後順序規劃，並採取適當墜落災害防止設施。；雇主使勞工從事屋頂作業時，應指派專人督導，並依下列規定辦理：一、…。三、於易踏穿材料構築之屋頂作業時，應先規劃安全通道，於屋架上設置適當強度，且寬度在三十公分以上之踏板，並於下方適當範圍裝設堅固格柵或安全網等防墜設施。但雇主設置踏板面積已覆蓋全部易踏穿屋頂或採取其他安全工法，致無踏穿墜落之虞者，不在此限。；於前項第三款之易踏穿材料構築屋頂作業時，雇主應指派屋頂作業主管於現場辦理下列事項：一、決定作業方法，指揮勞工作業。二、實施檢點，檢查材料、工具、器具等，並汰換不良品。三、監督勞工確實使用個人防護具。四、確認安全衛生設備及措施之有效狀況。五、前二款未確認前，應管制勞工或其他人員不得進入作業。六、其他為維持作業勞工安全衛生所必要之設備及措施。；雇主對於高度二公尺以上之屋頂、鋼梁、開口部分、階梯、樓梯、坡道、工作臺、擋土牆、擋土支撐、施工構臺、橋梁墩柱及橋梁上部結構、橋臺等場所作業，勞工有遭受墜落危險之虞者，應於該處設置護欄、護蓋或安全網等防護設備。",
    "罰鍰金額": "",
    "備註說明": ""
}