{"data":[{"\u767b\u8a18\u6a5f\u95dc":"\u65b0\u7af9\u7e23\u653f\u5e9c","\u6838\u51c6\u8a2d\u7acb\u65e5\u671f":{"year":2011,"month":2,"day":17},"\u6700\u8fd1\u7570\u52d5\u65e5\u671f":{"year":2021,"month":5,"day":13},"\u5546\u696d\u540d\u7a31":"\u5982\u610f\u6253\u5b57\u5370\u5237\u884c","\u8ca0\u8cac\u4eba\u59d3\u540d":"\u53e4\u5c55\u4efb","\u73fe\u6cc1":"\u6838\u51c6\u8a2d\u7acb","\u8cc7\u672c\u984d(\u5143)":"35,000","\u7d44\u7e54\u985e\u578b":"\u7368\u8cc7","\u5730\u5740":"\u65b0\u7af9\u7e23\u6e56\u53e3\u9109\u9cf3\u51f0\u675126\u9130\u4ec1\u548c\u8def85\u865f","\u71df\u696d\u9805\u76ee":"1\r\n\t\t\t\t\t\t\t\t\t\t\t\t\t\t\tIZ01010\r\n\t\t\t\t\t\t\t\t\t\t\t\t\t\t\t\u5f71\u5370\u696d\r\n\t\t\t\t\t\t\t\t\t\t\t\t\t\t\r\n\t\t\t\t\t\t\t\t\t\t\t\t\t\t\t2\r\n\t\t\t\t\t\t\t\t\t\t\t\t\t\t\tIZ02010\r\n\t\t\t\t\t\t\t\t\t\t\t\t\t\t\t\u6253\u5b57\u696d\r\n\t\t\t\t\t\t\t\t\t\t\t\t\t\t\r\n\t\t\t\t\t\t\t\t\t\t\t\t\t\t\t3\r\n\t\t\t\t\t\t\t\t\t\t\t\t\t\t\tC701010\r\n\t\t\t\t\t\t\t\t\t\t\t\t\t\t\t\u5370\u5237\u696d","\u51fa\u8cc7\u984d(\u5143)":{"\u53e4\u5c55\u4efb":"35000"},"url":"\/fts\/query\/QueryBusmDetail\/queryBusmDetail.do?objectId=SEIwMjc2NjczMjMzMzAwMDAwMDAwMDA2NjAwMTAz&banNo=02766732&banKey=33300000000006600103&disj=52FA13099B0B415B6068BD5CE8DA8A5D&fhl=zh_TW","\u8ca1\u653f\u90e8":{"\u71df\u696d\u4eba\u540d\u7a31":"\u5982\u610f\u6253\u5b57\u5370\u5237\u884c","\u8cc7\u672c\u984d":"35000","\u8a2d\u7acb\u65e5\u671f":{"year":1988,"month":2,"day":27},"\u4f7f\u7528\u7d71\u4e00\u767c\u7968":"Y","\u884c\u696d":[["160100","\u5370\u5237"],["820999","\u672a\u5206\u985e\u5176\u4ed6\u884c\u653f\u652f\u63f4\u670d\u52d9"]],"\u71df\u696d\u5730\u5740":"\u65b0\u7af9\u7e23\u6e56\u53e3\u9109\u9cf3\u51f0\u6751\uff12\uff16\u9130\u4ec1\u548c\u8def\uff18\uff15\u865f","\u8ca0\u8cac\u4eba\u59d3\u6c0f":"\u856d","\u7e3d\u6a5f\u69cb\u7d71\u4e00\u7de8\u865f":"","\u7d44\u7e54\u5225\u540d\u7a31":"\u7368\u8cc7"},"\u7d71\u4e00\u7de8\u865f":"02766732"},{"\u767b\u8a18\u6a5f\u95dc":"\u81fa\u5357\u5e02\u653f\u5e9c","\u6838\u51c6\u8a2d\u7acb\u65e5\u671f":{"year":1988,"month":6,"day":22},"\u6700\u8fd1\u7570\u52d5\u65e5\u671f":{"year":2018,"month":1,"day":8},"\u5546\u696d\u540d\u7a31":"\u5982\u610f\u6253\u5b57\u5370\u5237\u884c","\u8ca0\u8cac\u4eba\u59d3\u540d":"\u5433\u8cf4\u6dd1\u82ac","\u73fe\u6cc1":"\u6b47\u696d\uff0f\u64a4\u92b7","\u8cc7\u672c\u984d(\u5143)":"1,013,000","\u7d44\u7e54\u985e\u578b":"\u7368\u8cc7","\u5730\u5740":"\u81fa\u5357\u5e02\u6771\u5340\u6210\u5927\u91cc\u80b2\u6a02\u885757\u5df72\u5f046\u865f1\u6a13","\u71df\u696d\u9805\u76ee":"1\n\r\n\t\t\t\t\t\t\tIZ01010\n\r\n\t\t\t\t\t\t\t\u5f71\u5370\u696d\n\r\n\t\t\t\t\t\t\r\n\t\t\t\t\t\t\t2\n\r\n\t\t\t\t\t\t\tIZ02010\n\r\n\t\t\t\t\t\t\t\u6253\u5b57\u696d\n\r\n\t\t\t\t\t\t\r\n\t\t\t\t\t\t\t3\n\r\n\t\t\t\t\t\t\tIZ10010\n\r\n\t\t\t\t\t\t\t\u6392\u7248\u696d\n\r\n\t\t\t\t\t\t\r\n\t\t\t\t\t\t\t4\n\r\n\t\t\t\t\t\t\tF109070\n\r\n\t\t\t\t\t\t\t\u6587\u6559\u3001\u6a02\u5668\u3001\u80b2\u6a02\u7528\u54c1\u6279\u767c\u696d\n\r\n\t\t\t\t\t\t\r\n\t\t\t\t\t\t\t5\n\r\n\t\t\t\t\t\t\tF209060\n\r\n\t\t\t\t\t\t\t\u6587\u6559\u3001\u6a02\u5668\u3001\u80b2\u6a02\u7528\u54c1\u96f6\u552e\u696d\n\r\n\t\t\t\t\t\t\r\n\t\t\t\t\t\t\t6\n\r\n\t\t\t\t\t\t\tC701010\n\r\n\t\t\t\t\t\t\t\u5370\u5237\u696d\n\r\n\t\t\t\t\t\t\r\n\t\t\t\t\t\t\t7\n\r\n\t\t\t\t\t\t\tF113050\n\r\n\t\t\t\t\t\t\t\u96fb\u8166\u53ca\u4e8b\u52d9\u6027\u6a5f\u5668\u8a2d\u5099\u6279\u767c\u696d\n\r\n\t\t\t\t\t\t\r\n\t\t\t\t\t\t\t8\n\r\n\t\t\t\t\t\t\tF213030\n\r\n\t\t\t\t\t\t\t\u96fb\u8166\u53ca\u4e8b\u52d9\u6027\u6a5f\u5668\u8a2d\u5099\u96f6\u552e\u696d","\u51fa\u8cc7\u984d(\u5143)":{"\u5433\u8cf4\u6dd1\u82ac":"1013000"},"\u8ca1\u653f\u90e8":{"\u71df\u696d\u4eba\u540d\u7a31":"\u5982\u610f\u6253\u5b57\u5370\u5237\u884c","\u8cc7\u672c\u984d":"1013000","\u8a2d\u7acb\u65e5\u671f":{"year":1988,"month":6,"day":21},"\u4f7f\u7528\u7d71\u4e00\u767c\u7968":"Y","\u884c\u696d":[["820300","\u5f71\u5370\u670d\u52d9"],["820912","\u6587\u4ef6\u6253\u5b57\u3001\u64b0\u7a3f\u53ca\u901f\u8a18\u7b49\u670d\u52d9"],["476111","\u6587\u5177\u96f6\u552e"],["483111","\u96fb\u8166\u53ca\u96fb\u8166\u9031\u908a\u8a2d\u5099\u96f6\u552e"]],"\u71df\u696d\u5730\u5740":"\u81fa\u5357\u5e02\u6771\u5340\u6210\u5927\u91cc\u80b2\u6a02\u8857\uff15\uff17\u5df7\uff12\u5f04\uff16\u865f\uff11\u6a13","\u8ca0\u8cac\u4eba\u59d3\u6c0f":"\u5433","\u7e3d\u6a5f\u69cb\u7d71\u4e00\u7de8\u865f":""},"\u7d71\u4e00\u7de8\u865f":"06488268"}],"found":2}