{"data":[{"\u767b\u8a18\u6a5f\u95dc":"\u81fa\u5357\u5e02\u653f\u5e9c","\u6838\u51c6\u8a2d\u7acb\u65e5\u671f":{"year":2003,"month":8,"day":8},"\u6700\u8fd1\u7570\u52d5\u65e5\u671f":{"year":2004,"month":5,"day":21},"\u5546\u696d\u540d\u7a31":"\u6377\u8208\u5de5\u7a0b\u884c","\u8ca0\u8cac\u4eba\u59d3\u540d":"\u6797\u5efa\u5357","\u73fe\u6cc1":"\u6838\u51c6\u505c\u696d","\u8cc7\u672c\u984d(\u5143)":"200,000","\u7d44\u7e54\u985e\u578b":"\u7368\u8cc7","\u5730\u5740":"\u81fa\u5357\u5e02\u4e2d\u897f\u5340\u6587\u8ce2\u91cc\u548c\u5584\u885784\u5df78\u865f1\u6a13\uff08\u50c5\u4f9b\u8fa6\u516c\u5ba4\u4f7f\u7528\uff09","\u71df\u696d\u9805\u76ee":"1\r\n\r\n                    E801020\r\n\r\n                    \u9580\u7a97\u5b89\u88dd\u5de5\u7a0b\u696d\r\n\r\n              \r\n                    2\r\n\r\n                    E801030\r\n\r\n                    \u5ba4\u5167\u8f15\u92fc\u67b6\u5de5\u7a0b\u696d\r\n\r\n              \r\n                    3\r\n\r\n                    E901010\r\n\r\n                    \u6cb9\u6f06\u5de5\u7a0b\u696d\r\n\r\n              \r\n                    4\r\n\r\n                    E903010\r\n\r\n                    \u9632\u8755\u3001\u9632\u92b9\u5de5\u7a0b\u696d\r\n\r\n              \r\n                    5\r\n\r\n                    E599010\r\n\r\n                    \u914d\u7ba1\u5de5\u7a0b\u696d\r\n\r\n              \r\n                    6\r\n\r\n                    F106010\r\n\r\n                    \u4e94\u91d1\u6279\u767c\u696d\r\n\r\n              \r\n                    7\r\n\r\n                    F206010\r\n\r\n                    \u4e94\u91d1\u96f6\u552e\u696d","\u8ca1\u653f\u90e8":{},"\u7d71\u4e00\u7de8\u865f":"98807887"},{"\u767b\u8a18\u6a5f\u95dc":"\u65b0\u7af9\u7e23\u653f\u5e9c","\u6838\u51c6\u8a2d\u7acb\u65e5\u671f":{"year":2014,"month":8,"day":22},"\u6700\u8fd1\u7570\u52d5\u65e5\u671f":{"year":2021,"month":2,"day":3},"\u5546\u696d\u540d\u7a31":"\u6377\u8208\u5de5\u7a0b\u884c","\u8ca0\u8cac\u4eba\u59d3\u540d":"\u6f58\u653f\u6377","\u73fe\u6cc1":"\u6b47\u696d","\u8cc7\u672c\u984d(\u5143)":"200,000","\u7d44\u7e54\u985e\u578b":"\u7368\u8cc7","\u5730\u5740":"\u65b0\u7af9\u7e23\u828e\u6797\u9109\u6c34\u5751\u6751\u5609\u6176109\u865f1\u6a13","\u71df\u696d\u9805\u76ee":"1\r\n\t\t\t\t\t\t\t\t\t\t\t\t\t\t\tE603110\r\n\t\t\t\t\t\t\t\t\t\t\t\t\t\t\t\u51b7\u4f5c\u5de5\u7a0b\u696d\r\n\t\t\t\t\t\t\t\t\t\t\t\t\t\t\r\n\t\t\t\t\t\t\t\t\t\t\t\t\t\t\t2\r\n\t\t\t\t\t\t\t\t\t\t\t\t\t\t\tE603120\r\n\t\t\t\t\t\t\t\t\t\t\t\t\t\t\t\u5674\u7802\u5de5\u7a0b\u696d\r\n\t\t\t\t\t\t\t\t\t\t\t\t\t\t\r\n\t\t\t\t\t\t\t\t\t\t\t\t\t\t\t3\r\n\t\t\t\t\t\t\t\t\t\t\t\t\t\t\tE603100\r\n\t\t\t\t\t\t\t\t\t\t\t\t\t\t\t\u96fb\u710a\u5de5\u7a0b\u696d\r\n\t\t\t\t\t\t\t\t\t\t\t\t\t\t\r\n\t\t\t\t\t\t\t\t\t\t\t\t\t\t\t4\r\n\t\t\t\t\t\t\t\t\t\t\t\t\t\t\tEZ07010\r\n\t\t\t\t\t\t\t\t\t\t\t\t\t\t\t\u947d\u5b54\u5de5\u7a0b\u696d\r\n\t\t\t\t\t\t\t\t\t\t\t\t\t\t\r\n\t\t\t\t\t\t\t\t\t\t\t\t\t\t\t5\r\n\t\t\t\t\t\t\t\t\t\t\t\t\t\t\tE901010\r\n\t\t\t\t\t\t\t\t\t\t\t\t\t\t\t\u6cb9\u6f06\u5de5\u7a0b\u696d\r\n\t\t\t\t\t\t\t\t\t\t\t\t\t\t\r\n\t\t\t\t\t\t\t\t\t\t\t\t\t\t\t6\r\n\t\t\t\t\t\t\t\t\t\t\t\t\t\t\tE903010\r\n\t\t\t\t\t\t\t\t\t\t\t\t\t\t\t\u9632\u8755\u3001\u9632\u92b9\u5de5\u7a0b\u696d\r\n\t\t\t\t\t\t\t\t\t\t\t\t\t\t\r\n\t\t\t\t\t\t\t\t\t\t\t\t\t\t\t7\r\n\t\t\t\t\t\t\t\t\t\t\t\t\t\t\tE599010\r\n\t\t\t\t\t\t\t\t\t\t\t\t\t\t\t\u914d\u7ba1\u5de5\u7a0b\u696d","\u51fa\u8cc7\u984d(\u5143)":{"\u6f58\u653f\u6377":"200000"},"url":"\/fts\/query\/QueryBusmDetail\/queryBusmDetail.do?objectId=SEI0MDk4NDk1NTMzMzAwMDAwMDAwMDEwNzcwMDUz&banNo=40984955&banKey=33300000000010770053&disj=5EF2AB9C76CF32AB3ECB5336C3273A78&fhl=zh_TW","\u8ca1\u653f\u90e8":{"\u71df\u696d\u4eba\u540d\u7a31":"\u6377\u8208\u5de5\u7a0b\u884c","\u8cc7\u672c\u984d":"200000","\u8a2d\u7acb\u65e5\u671f":{"year":2014,"month":8,"day":22},"\u4f7f\u7528\u7d71\u4e00\u767c\u7968":"N","\u884c\u696d":[["434012","\u6cb9\u6f06\u7c89\u5237\u3001\u58c1\u98fe\uff08\u7d19\uff09\u9ecf\u8cbc\u5de5\u7a0b"],["434099","\u5176\u4ed6\u5efa\u7269\u5b8c\u5de5\u88dd\u4fee\u5de5\u7a0b"]],"\u71df\u696d\u5730\u5740":"\u65b0\u7af9\u7e23\u828e\u6797\u9109\u6c34\u5751\u6751\u5609\u6176\uff11\uff10\uff19\u865f\uff11\u6a13","\u8ca0\u8cac\u4eba\u59d3\u6c0f":"\u6f58","\u7e3d\u6a5f\u69cb\u7d71\u4e00\u7de8\u865f":"","\u7d44\u7e54\u5225\u540d\u7a31":"\u7368\u8cc7"},"\u7d71\u4e00\u7de8\u865f":"40984955"},{"\u767b\u8a18\u6a5f\u95dc":"\u65b0\u5317\u5e02\u653f\u5e9c\u7d93\u6fdf\u767c\u5c55\u5c40","\u6838\u51c6\u8a2d\u7acb\u65e5\u671f":{"year":2006,"month":10,"day":30},"\u6700\u8fd1\u7570\u52d5\u65e5\u671f":{"year":2025,"month":3,"day":7},"\u5546\u696d\u540d\u7a31":"\u6377\u8208\u5de5\u7a0b\u884c","\u8ca0\u8cac\u4eba\u59d3\u540d":"\u6d2a\u9e97\u79cb","\u8cc7\u672c\u984d(\u5143)":"200,000","\u7d44\u7e54\u985e\u578b":"\u7368\u8cc7","\u5730\u5740":"\u65b0\u5317\u5e02\u6c50\u6b62\u5340\u798f\u5fb7\u4e09\u8def73\u865f5\u6a13","\u71df\u696d\u9805\u76ee":"1\r\n\t\t\t\t\t\t\t\t\t\t\t\t\t\t\tEZ02010\r\n\t\t\t\t\t\t\t\t\t\t\t\t\t\t\t\u8d77\u91cd\u5de5\u7a0b\u696d\r\n\t\t\t\t\t\t\t\t\t\t\t\t\t\t\r\n\t\t\t\t\t\t\t\t\t\t\t\t\t\t\t2\r\n\t\t\t\t\t\t\t\t\t\t\t\t\t\t\tF213080\r\n\t\t\t\t\t\t\t\t\t\t\t\t\t\t\t\u6a5f\u68b0\u5668\u5177\u96f6\u552e\u696d\r\n\t\t\t\t\t\t\t\t\t\t\t\t\t\t\r\n\t\t\t\t\t\t\t\t\t\t\t\t\t\t\t3\r\n\t\t\t\t\t\t\t\t\t\t\t\t\t\t\tF401010\r\n\t\t\t\t\t\t\t\t\t\t\t\t\t\t\t\u570b\u969b\u8cbf\u6613\u696d\r\n\t\t\t\t\t\t\t\t\t\t\t\t\t\t\r\n\t\t\t\t\t\t\t\t\t\t\t\t\t\t\t4\r\n\t\t\t\t\t\t\t\t\t\t\t\t\t\t\tE604010\r\n\t\t\t\t\t\t\t\t\t\t\t\t\t\t\t\u6a5f\u68b0\u5b89\u88dd\u696d\r\n\t\t\t\t\t\t\t\t\t\t\t\t\t\t\r\n\t\t\t\t\t\t\t\t\t\t\t\t\t\t\t5\r\n\t\t\t\t\t\t\t\t\t\t\t\t\t\t\tEZ99990\r\n\t\t\t\t\t\t\t\t\t\t\t\t\t\t\t\u5176\u4ed6\u5de5\u7a0b\u696d\r\n\t\t\t\t\t\t\t\t\t\t\t\t\t\t\r\n\t\t\t\t\t\t\t\t\t\t\t\t\t\t\t6\r\n\t\t\t\t\t\t\t\t\t\t\t\t\t\t\tJE01010\r\n\t\t\t\t\t\t\t\t\t\t\t\t\t\t\t\u79df\u8cc3\u696d","\u51fa\u8cc7\u984d(\u5143)":{"\u6d2a\u9e97\u79cb":"200000"},"url":"\/fts\/query\/QueryBusmDetail\/queryBusmDetail.do?objectId=SEIyMTUxMDEyOTQzMTAwMDAwMDAwMDAwNTI5MTIw&banNo=21510129&banKey=43100000000000529120&disj=DE71A724D0D94242F2FB10A32B53C300&fhl=zh_TW","\u767b\u8a18\u73fe\u6cc1":"\u6838\u51c6\u8a2d\u7acb","\u8ca1\u653f\u90e8":{"\u71df\u696d\u4eba\u540d\u7a31":"\u6377\u8208\u5de5\u7a0b\u884c","\u8cc7\u672c\u984d":"200000","\u8a2d\u7acb\u65e5\u671f":{"year":2005,"month":3,"day":14},"\u4f7f\u7528\u7d71\u4e00\u767c\u7968":"Y","\u884c\u696d":[["464999","\u672a\u5206\u985e\u5176\u4ed6\u6a5f\u68b0\u5668\u5177\u6279\u767c"],["451099","\u5176\u4ed6\u5546\u54c1\u6279\u767c\u7d93\u7d00"],["439099","\u672a\u5206\u985e\u5176\u4ed6\u5c08\u9580\u71df\u9020"]],"\u71df\u696d\u5730\u5740":"\u65b0\u5317\u5e02\u6c50\u6b62\u5340\u5eb7\u798f\u91cc\u798f\u5fb7\u4e09\u8def\uff17\uff13\u865f\uff15\u6a13","\u8ca0\u8cac\u4eba\u59d3\u6c0f":"\u9ad8","\u7e3d\u6a5f\u69cb\u7d71\u4e00\u7de8\u865f":"","\u7d44\u7e54\u5225\u540d\u7a31":"\u7368\u8cc7"},"\u7d71\u4e00\u7de8\u865f":"21510129"}],"found":3}