{"data":[{"\u767b\u8a18\u6a5f\u95dc":"\u57fa\u9686\u5e02\u653f\u5e9c","\u6838\u51c6\u8a2d\u7acb\u65e5\u671f":{"year":2012,"month":2,"day":21},"\u6700\u8fd1\u7570\u52d5\u65e5\u671f":{"year":2024,"month":10,"day":9},"\u5546\u696d\u540d\u7a31":"\u8072\u9a65\u97f3\u6a02\u6587\u5316\u50b3\u64ad\u5de5\u4f5c\u5ba4","\u8ca0\u8cac\u4eba\u59d3\u540d":"\u8881\u9a65\u5b89","\u8cc7\u672c\u984d(\u5143)":"200,000","\u7d44\u7e54\u985e\u578b":"\u7368\u8cc7","\u5730\u5740":"\u57fa\u9686\u5e02\u6696\u6696\u5340\u6e90\u9060\u8def165-3\u865f6\u6a13","\u71df\u696d\u9805\u76ee":"1\r\n\t\t\t\t\t\t\t\t\t\t\t\t\t\t\tJ305010\r\n\t\t\t\t\t\t\t\t\t\t\t\t\t\t\t\u6709\u8072\u51fa\u7248\u696d\r\n\t\t\t\t\t\t\t\t\t\t\t\t\t\t\r\n\t\t\t\t\t\t\t\t\t\t\t\t\t\t\t2\r\n\t\t\t\t\t\t\t\t\t\t\t\t\t\t\tJ601010\r\n\t\t\t\t\t\t\t\t\t\t\t\t\t\t\t\u85dd\u6587\u670d\u52d9\u696d\r\n\t\t\t\t\t\t\t\t\t\t\t\t\t\t\r\n\t\t\t\t\t\t\t\t\t\t\t\t\t\t\t3\r\n\t\t\t\t\t\t\t\t\t\t\t\t\t\t\tJ602010\r\n\t\t\t\t\t\t\t\t\t\t\t\t\t\t\t\u6f14\u85dd\u6d3b\u52d5\u696d\r\n\t\t\t\t\t\t\t\t\t\t\t\t\t\t\r\n\t\t\t\t\t\t\t\t\t\t\t\t\t\t\t4\r\n\t\t\t\t\t\t\t\t\t\t\t\t\t\t\tJ701090\r\n\t\t\t\t\t\t\t\t\t\t\t\t\t\t\t\u9304\u5f71\u7bc0\u76ee\u5e36\u64ad\u6620\u696d\r\n\t\t\t\t\t\t\t\t\t\t\t\t\t\t\r\n\t\t\t\t\t\t\t\t\t\t\t\t\t\t\t5\r\n\t\t\t\t\t\t\t\t\t\t\t\t\t\t\tJB01010\r\n\t\t\t\t\t\t\t\t\t\t\t\t\t\t\t\u6703\u8b70\u53ca\u5c55\u89bd\u670d\u52d9\u696d\r\n\t\t\t\t\t\t\t\t\t\t\t\t\t\t\r\n\t\t\t\t\t\t\t\t\t\t\t\t\t\t\t6\r\n\t\t\t\t\t\t\t\t\t\t\t\t\t\t\tJZ99030\r\n\t\t\t\t\t\t\t\t\t\t\t\t\t\t\t\u651d\u5f71\u696d\r\n\t\t\t\t\t\t\t\t\t\t\t\t\t\t\r\n\t\t\t\t\t\t\t\t\t\t\t\t\t\t\t7\r\n\t\t\t\t\t\t\t\t\t\t\t\t\t\t\tJZ99090\r\n\t\t\t\t\t\t\t\t\t\t\t\t\t\t\t\u559c\u6176\u7d9c\u5408\u670d\u52d9\u696d\r\n\t\t\t\t\t\t\t\t\t\t\t\t\t\t\r\n\t\t\t\t\t\t\t\t\t\t\t\t\t\t\t8\r\n\t\t\t\t\t\t\t\t\t\t\t\t\t\t\tJZ99990\r\n\t\t\t\t\t\t\t\t\t\t\t\t\t\t\t\u672a\u5206\u985e\u5176\u4ed6\u670d\u52d9\u696d\r\n\t\t\t\t\t\t\t\t\t\t\t\t\t\t\r\n\t\t\t\t\t\t\t\t\t\t\t\t\t\t\t9\r\n\t\t\t\t\t\t\t\t\t\t\t\t\t\t\tJ399990\r\n\t\t\t\t\t\t\t\t\t\t\t\t\t\t\t\u5176\u4ed6\u51fa\u7248\u696d\r\n\t\t\t\t\t\t\t\t\t\t\t\t\t\t\r\n\t\t\t\t\t\t\t\t\t\t\t\t\t\t\t10\r\n\t\t\t\t\t\t\t\t\t\t\t\t\t\t\tJA05010\r\n\t\t\t\t\t\t\t\t\t\t\t\t\t\t\t\u7559\u3001\u904a\u5b78\u670d\u52d9\u696d","\u51fa\u8cc7\u984d(\u5143)":{"\u8881\u9a65\u5b89":"200000"},"url":"\/fts\/query\/QueryBusmDetail\/queryBusmDetail.do?objectId=SEIyNjc2MDYxODMxMTAwMDAwMDAwMDE5MDExOTky&banNo=26760618&banKey=31100000000019011992&disj=F0BC2A2F625424354D33969F26C9BEC9&fhl=zh_TW","\u767b\u8a18\u73fe\u6cc1":"\u6b47\u696d","\u8ca1\u653f\u90e8":{"\u71df\u696d\u4eba\u540d\u7a31":"\u8072\u9a65\u97f3\u6a02\u6587\u5316\u50b3\u64ad\u5de5\u4f5c\u5ba4","\u8cc7\u672c\u984d":"200000","\u8a2d\u7acb\u65e5\u671f":{"year":2012,"month":2,"day":21},"\u4f7f\u7528\u7d71\u4e00\u767c\u7968":"Y","\u884c\u696d":[["902099","\u5176\u4ed6\u85dd\u8853\u8868\u6f14"],["592016","\u96fb\u8996\u7bc0\u76ee\u9304\u97f3\u3001\u97f3\u6548"]],"\u71df\u696d\u5730\u5740":"\u57fa\u9686\u5e02\u6696\u6696\u5340\u7887\u548c\u91cc\u6e90\u9060\u8def\uff11\uff16\uff15\u2015\uff13\u865f\uff16\u6a13","\u8ca0\u8cac\u4eba\u59d3\u6c0f":"\u8881","\u7e3d\u6a5f\u69cb\u7d71\u4e00\u7de8\u865f":"","\u7d44\u7e54\u5225\u540d\u7a31":"\u7368\u8cc7"},"\u7d71\u4e00\u7de8\u865f":"26760618"}],"found":1}