{"data":[{"\u767b\u8a18\u6a5f\u95dc":"\u65b0\u5317\u5e02\u653f\u5e9c\u7d93\u6fdf\u767c\u5c55\u5c40","\u6838\u51c6\u8a2d\u7acb\u65e5\u671f":{"year":2024,"month":3,"day":27},"\u6700\u8fd1\u7570\u52d5\u65e5\u671f":{"year":2024,"month":3,"day":27},"\u5546\u696d\u540d\u7a31":"\u82ae\u69ae\u5de5\u7a0b\u884c","\u8ca0\u8cac\u4eba\u59d3\u540d":"\u6f58\u745e\u9023","\u73fe\u6cc1":"\u6838\u51c6\u8a2d\u7acb","\u8cc7\u672c\u984d(\u5143)":"50,000","\u7d44\u7e54\u985e\u578b":"\u7368\u8cc7","\u5730\u5740":"\u65b0\u5317\u5e02\u9daf\u6b4c\u5340\u9cf3\u9cf4\u8def515\u865f4\u6a13","\u71df\u696d\u9805\u76ee":"1\r\n\t\t\t\t\t\t\t\t\t\t\t\t\t\t\tE599010\r\n\t\t\t\t\t\t\t\t\t\t\t\t\t\t\t\u914d\u7ba1\u5de5\u7a0b\u696d\r\n\t\t\t\t\t\t\t\t\t\t\t\t\t\t\r\n\t\t\t\t\t\t\t\t\t\t\t\t\t\t\t2\r\n\t\t\t\t\t\t\t\t\t\t\t\t\t\t\tCA01050\r\n\t\t\t\t\t\t\t\t\t\t\t\t\t\t\t\u92fc\u6750\u4e8c\u6b21\u52a0\u5de5\u696d\r\n\t\t\t\t\t\t\t\t\t\t\t\t\t\t\r\n\t\t\t\t\t\t\t\t\t\t\t\t\t\t\t3\r\n\t\t\t\t\t\t\t\t\t\t\t\t\t\t\tE603010\r\n\t\t\t\t\t\t\t\t\t\t\t\t\t\t\t\u96fb\u7e9c\u5b89\u88dd\u5de5\u7a0b\u696d\r\n\t\t\t\t\t\t\t\t\t\t\t\t\t\t\r\n\t\t\t\t\t\t\t\t\t\t\t\t\t\t\t4\r\n\t\t\t\t\t\t\t\t\t\t\t\t\t\t\tE607010\r\n\t\t\t\t\t\t\t\t\t\t\t\t\t\t\t\u592a\u967d\u71b1\u80fd\u8a2d\u5099\u5b89\u88dd\u5de5\u7a0b\u696d\r\n\t\t\t\t\t\t\t\t\t\t\t\t\t\t\r\n\t\t\t\t\t\t\t\t\t\t\t\t\t\t\t5\r\n\t\t\t\t\t\t\t\t\t\t\t\t\t\t\tZZ99999\r\n\t\t\t\t\t\t\t\t\t\t\t\t\t\t\t\u9664\u8a31\u53ef\u696d\u52d9\u5916\uff0c\u5f97\u7d93\u71df\u6cd5\u4ee4\u975e\u7981\u6b62\u6216\u9650\u5236\u4e4b\u696d\u52d9","\u51fa\u8cc7\u984d(\u5143)":{"\u6f58\u745e\u9023":"50000"},"url":"\/fts\/query\/QueryBusmDetail\/queryBusmDetail.do?objectId=SEI4MDAxNzMyNDMzMTAwMDAwMDAwMDI0MDYxODU1&banNo=80017324&banKey=33100000000024061855&disj=9678FE9CEA769450D9D4F626FE281C17&fhl=zh_TW","\u8ca1\u653f\u90e8":{"\u71df\u696d\u4eba\u540d\u7a31":"\u82ae\u69ae\u5de5\u7a0b\u884c","\u8cc7\u672c\u984d":"50000","\u8a2d\u7acb\u65e5\u671f":{"year":2024,"month":3,"day":27},"\u4f7f\u7528\u7d71\u4e00\u767c\u7968":"Y","\u884c\u696d":[["433212","\u7ba1\u9053\u5de5\u7a0b"],["433117","\u96fb\u7e9c\u88dd\u4fee\u5de5\u7a0b"]],"\u71df\u696d\u5730\u5740":"\u65b0\u5317\u5e02\u9daf\u6b4c\u5340\u9cf3\u9cf4\u91cc\u9cf3\u9cf4\u8def\uff15\uff11\uff15\u865f\uff14\u6a13","\u7e3d\u6a5f\u69cb\u7d71\u4e00\u7de8\u865f":"","\u7d44\u7e54\u5225\u540d\u7a31":"\u7368\u8cc7"},"\u7d71\u4e00\u7de8\u865f":"80017324"},{"\u767b\u8a18\u6a5f\u95dc":"\u96f2\u6797\u7e23\u653f\u5e9c","\u6838\u51c6\u8a2d\u7acb\u65e5\u671f":{"year":2011,"month":11,"day":8},"\u6700\u8fd1\u7570\u52d5\u65e5\u671f":{"year":2021,"month":1,"day":4},"\u5546\u696d\u540d\u7a31":"\u82ae\u69ae\u5de5\u7a0b\u884c","\u8ca0\u8cac\u4eba\u59d3\u540d":"\u6d82\u9326\u5149","\u73fe\u6cc1":"\u6838\u51c6\u8a2d\u7acb","\u8cc7\u672c\u984d(\u5143)":"200,000","\u7d44\u7e54\u985e\u578b":"\u7368\u8cc7","\u5730\u5740":"\u96f2\u6797\u7e23\u9ea5\u5bee\u9109\u9ea5\u8c50\u6751\u65b0\u8208\u8def\u6a6b\u8857\u5df7\uff12\uff12\u865f","\u71df\u696d\u9805\u76ee":"1\r\n\t\t\t\t\t\t\t\t\t\t\t\t\t\t\tE599010\r\n\t\t\t\t\t\t\t\t\t\t\t\t\t\t\t\u914d\u7ba1\u5de5\u7a0b\u696d\r\n\t\t\t\t\t\t\t\t\t\t\t\t\t\t\r\n\t\t\t\t\t\t\t\t\t\t\t\t\t\t\t2\r\n\t\t\t\t\t\t\t\t\t\t\t\t\t\t\tE603100\r\n\t\t\t\t\t\t\t\t\t\t\t\t\t\t\t\u96fb\u710a\u5de5\u7a0b\u696d\r\n\t\t\t\t\t\t\t\t\t\t\t\t\t\t\r\n\t\t\t\t\t\t\t\t\t\t\t\t\t\t\t3\r\n\t\t\t\t\t\t\t\t\t\t\t\t\t\t\tE603110\r\n\t\t\t\t\t\t\t\t\t\t\t\t\t\t\t\u51b7\u4f5c\u5de5\u7a0b\u696d\r\n\t\t\t\t\t\t\t\t\t\t\t\t\t\t\r\n\t\t\t\t\t\t\t\t\t\t\t\t\t\t\t4\r\n\t\t\t\t\t\t\t\t\t\t\t\t\t\t\tE603120\r\n\t\t\t\t\t\t\t\t\t\t\t\t\t\t\t\u5674\u7802\u5de5\u7a0b\u696d\r\n\t\t\t\t\t\t\t\t\t\t\t\t\t\t\r\n\t\t\t\t\t\t\t\t\t\t\t\t\t\t\t5\r\n\t\t\t\t\t\t\t\t\t\t\t\t\t\t\tE604010\r\n\t\t\t\t\t\t\t\t\t\t\t\t\t\t\t\u6a5f\u68b0\u5b89\u88dd\u696d\r\n\t\t\t\t\t\t\t\t\t\t\t\t\t\t\r\n\t\t\t\t\t\t\t\t\t\t\t\t\t\t\t6\r\n\t\t\t\t\t\t\t\t\t\t\t\t\t\t\tE801030\r\n\t\t\t\t\t\t\t\t\t\t\t\t\t\t\t\u5ba4\u5167\u8f15\u92fc\u67b6\u5de5\u7a0b\u696d\r\n\t\t\t\t\t\t\t\t\t\t\t\t\t\t\r\n\t\t\t\t\t\t\t\t\t\t\t\t\t\t\t7\r\n\t\t\t\t\t\t\t\t\t\t\t\t\t\t\tE901010\r\n\t\t\t\t\t\t\t\t\t\t\t\t\t\t\t\u6cb9\u6f06\u5de5\u7a0b\u696d\r\n\t\t\t\t\t\t\t\t\t\t\t\t\t\t\r\n\t\t\t\t\t\t\t\t\t\t\t\t\t\t\t8\r\n\t\t\t\t\t\t\t\t\t\t\t\t\t\t\tEZ15010\r\n\t\t\t\t\t\t\t\t\t\t\t\t\t\t\t\u4fdd\u6eab\u3001\u4fdd\u51b7\u5b89\u88dd\u5de5\u7a0b\u696d\r\n\t\t\t\t\t\t\t\t\t\t\t\t\t\t\r\n\t\t\t\t\t\t\t\t\t\t\t\t\t\t\t9\r\n\t\t\t\t\t\t\t\t\t\t\t\t\t\t\tEZ99990\r\n\t\t\t\t\t\t\t\t\t\t\t\t\t\t\t\u5176\u4ed6\u5de5\u7a0b\u696d\r\n\t\t\t\t\t\t\t\t\t\t\t\t\t\t\r\n\t\t\t\t\t\t\t\t\t\t\t\t\t\t\t10\r\n\t\t\t\t\t\t\t\t\t\t\t\t\t\t\tZZ99999\r\n\t\t\t\t\t\t\t\t\t\t\t\t\t\t\t\u9664\u8a31\u53ef\u696d\u52d9\u5916\uff0c\u5f97\u7d93\u71df\u6cd5\u4ee4\u975e\u7981\u6b62\u6216\u9650\u5236\u4e4b\u696d\u52d9","\u51fa\u8cc7\u984d(\u5143)":{"\u6d82\u9326\u5149":"200000"},"url":"\/fts\/query\/QueryBusmDetail\/queryBusmDetail.do?objectId=SEIyNTQ5MzczMzMzOTAwMDAwMDAwMDA3NDQ3ODgz&banNo=25493733&banKey=33900000000007447883&disj=1BD75156EAAF8A8357095607D08903E0&fhl=zh_TW","\u8ca1\u653f\u90e8":{"\u71df\u696d\u4eba\u540d\u7a31":"\u82ae\u69ae\u5de5\u7a0b\u884c","\u8cc7\u672c\u984d":"200000","\u8a2d\u7acb\u65e5\u671f":{"year":2011,"month":11,"day":8},"\u4f7f\u7528\u7d71\u4e00\u767c\u7968":"Y","\u884c\u696d":[["433212","\u7ba1\u9053\u5de5\u7a0b"],["439099","\u672a\u5206\u985e\u5176\u4ed6\u5c08\u9580\u71df\u9020"]],"\u71df\u696d\u5730\u5740":"\u96f2\u6797\u7e23\u9ea5\u5bee\u9109\u9ea5\u8c50\u6751\u65b0\u8208\u8def\u6a6b\u8857\u5df7\uff12\uff12\u865f","\u8ca0\u8cac\u4eba\u59d3\u6c0f":"\u5eb7","\u7e3d\u6a5f\u69cb\u7d71\u4e00\u7de8\u865f":"","\u7d44\u7e54\u5225\u540d\u7a31":"\u7368\u8cc7"},"\u7d71\u4e00\u7de8\u865f":"25493733"}],"found":2}