{"data":[{"\u767b\u8a18\u6a5f\u95dc":"\u82b1\u84ee\u7e23\u653f\u5e9c","\u6838\u51c6\u8a2d\u7acb\u65e5\u671f":{"year":2005,"month":6,"day":16},"\u6700\u8fd1\u7570\u52d5\u65e5\u671f":{"year":2006,"month":11,"day":2},"\u5546\u696d\u540d\u7a31":"\u8302\u7fa4\u6c34\u96fb\u5de5\u7a0b\u884c","\u8ca0\u8cac\u4eba\u59d3\u540d":"\u5b6b\u6167\u59dd","\u73fe\u6cc1":"\u6838\u51c6\u8a2d\u7acb","\u8cc7\u672c\u984d(\u5143)":"4,000,000","\u7d44\u7e54\u985e\u578b":"\u7368\u8cc7","\u5730\u5740":"\u82b1\u84ee\u7e23\u5409\u5b89\u9109\u5409\u5b89\u6751\u4e2d\u592e\u8def\uff12\u6bb5\uff11\uff13\uff19\u5df7\uff11\uff17\u865f\uff11\u6a13","\u71df\u696d\u9805\u76ee":"1\r\n\r\n                    F213010\r\n\r\n                    \u96fb\u5668\u96f6\u552e\u696d\r\n\r\n              \r\n                    2\r\n\r\n                    F211010\r\n\r\n                    \u5efa\u6750\u96f6\u552e\u696d\r\n\r\n              \r\n                    3\r\n\r\n                    F206040\r\n\r\n                    \u6c34\u5668\u6750\u6599\u96f6\u552e\u696d\r\n\r\n              \r\n                    4\r\n\r\n                    F207010\r\n\r\n                    \u6f06\u6599\u3001\u5857\u6599\u96f6\u552e\u696d\r\n\r\n              \r\n                    5\r\n\r\n                    E599010\r\n\r\n                    \u914d\u7ba1\u5de5\u7a0b\u696d\r\n\r\n              \r\n                    6\r\n\r\n                    IZ12010\r\n\r\n                    \u4eba\u529b\u6d3e\u9063\u696d\r\n\r\n              \r\n                    7\r\n\r\n                    E601010\r\n\r\n                    \u96fb\u5668\u627f\u88dd\u696d\r\n\r\n              \r\n                    8\r\n\r\n                    E601020\r\n\r\n                    \u96fb\u5668\u5b89\u88dd\u696d\r\n\r\n              \r\n                    9\r\n\r\n                    E501011\r\n\r\n                    \u81ea\u4f86\u6c34\u7ba1\u627f\u88dd\u5546\r\n\r\n              \r\n                    10\r\n\r\n                    E603040\r\n\r\n                    \u6d88\u9632\u5b89\u5168\u8a2d\u5099\u5b89\u88dd\u5de5\u7a0b\u696d\r\n\r\n              \r\n                    11\r\n\r\n                    F117010\r\n\r\n                    \u6d88\u9632\u5b89\u5168\u8a2d\u5099\u6279\u767c\u696d\r\n\r\n              \r\n                    12\r\n\r\n                    EZ07010\r\n\r\n                    \u947d\u5b54\u5de5\u7a0b\u696d\r\n\r\n              \r\n                    13\r\n\r\n                    EZ99990\r\n\r\n                    \u5176\u4ed6\u5de5\u7a0b\u696d","\u8ca1\u653f\u90e8":{"\u71df\u696d\u4eba\u540d\u7a31":"\u8302\u7fa4\u6c34\u96fb\u5de5\u7a0b\u884c","\u8cc7\u672c\u984d":"4000000","\u8a2d\u7acb\u65e5\u671f":{"year":2005,"month":6,"day":9},"\u4f7f\u7528\u7d71\u4e00\u767c\u7968":"Y","\u884c\u696d":[["433212","\u7ba1\u9053\u5de5\u7a0b"],["481011","\u6f06\u6599\u53ca\u5857\u6599\u96f6\u552e"],["474999","\u672a\u5206\u985e\u5176\u4ed6\u5bb6\u7528\u5668\u5177\u53ca\u7528\u54c1\u96f6\u552e"],["781011","\u79fb\u5de5\u4ef2\u4ecb"]],"\u71df\u696d\u5730\u5740":"\u82b1\u84ee\u7e23\u5409\u5b89\u9109\u5409\u5b89\u6751\u4e2d\u592e\u8def\uff12\u6bb5\uff11\uff13\uff19\u5df7\uff11\uff17\u865f\uff11\u6a13","\u8ca0\u8cac\u4eba\u59d3\u6c0f":"\u5b6b","\u7e3d\u6a5f\u69cb\u7d71\u4e00\u7de8\u865f":"","\u7d44\u7e54\u5225\u540d\u7a31":"\u7368\u8cc7"},"\u7d71\u4e00\u7de8\u865f":"21592352"}],"found":1}