{
    "主管機關": "桃園市",
    "公告日期": "20181011",
    "處分日期": "20180827",
    "處分字號": "府勞檢字第1070217950號",
    "事業單位名稱或負責人": "全泓營造有限公司(徐立芸)",
    "違法法規法條": "職業安全衛生設施規則第155條之1第1款暨職業安全衛生法第6條第1項;職業安全衛生設施規則第155條之1第4款暨職業安全衛生法第6條第1項;職業安全衛生設施規則第230條第1項第3款暨職業安全衛生法第6條第1項;職業安全衛生設施規則第230條第1項第4款暨職業安全衛生法第6條第1項;職業安全衛生設施規則第243條第1項暨職業安全衛生法第6條第1項;營造安全衛生設施標準第11條之1暨職業安全衛生法第6條第1項;營造安全衛生設施標準第19條第1項暨職業安全衛生法第6條第1項;營造安全衛生設施標準第59條第4款暨職業安全衛生法第6條第1項",
    "違反法規內容": "雇主使勞工以捲揚機等吊運物料時，應依下列規定辦理：一、安裝前須核對並確認設計資料及強度計算書。二、…。;雇主使勞工以捲揚機等吊運物料時，應依下列規定辦理：一、…。四、吊鉤或吊具應有防止吊舉中所吊物體脫落之裝置。五、…。;雇主對於使用之合梯，應符合下列規定：一、…。三、梯腳與地面之角度應在七十五度以內，且兩梯腳間有金屬等硬質繫材扣牢，腳部有防滑絕緣腳座套。四、…。;雇主對於使用之合梯，應符合下列規定：一、…。四、有安全之防滑梯面。;雇主對於使用對地電壓在一百五十伏特以上移動式或攜帶式電動機具，或於含水或被其他導電度高之液體濕潤之潮濕場所、金屬板上或鋼架上等導電性良好場所使用移動式或攜帶式電動機具，為防止因漏電而生感電危害，應於各該電動機具之連接電路上設置適合其規格，具有高敏感度、高速型，能確實動作之防止感電用漏電斷路器。;雇主對於進入營繕工程工作場所作業人員，應提供適當安全帽，並使其正確戴用。;雇主對於高度二公尺以上之屋頂、鋼樑、開口部分、階梯、樓梯、坡道、工作臺、擋土牆、擋土支撐、施工構臺、橋樑墩柱及橋樑上部結構、橋臺等場所作業，勞工有遭受墜落危險之虞者，應於該處設置護欄、護蓋或安全網等防護設備。;雇主對於鋼管施工架之設置，應依下列規定辦理：一、…。四、構件之連接部分或交叉部分，應以適當之金屬附屬配件確實連接固定，並以適當之斜撐材補強。但系統式施工架應以輪盤及插銷扣件等組配件連接。五、…。",
    "罰鍰金額": "",
    "備註說明": ""
}