{
    "主管機關": "桃園市",
    "公告日期": "20181011",
    "處分日期": "20180814",
    "處分字號": "府勞檢字第1070202992號",
    "事業單位名稱或負責人": "泰翔工業股份有限公司(李大權)",
    "違法法規法條": "粉塵危害預防標準第6條暨職業安全衛生法第16條第1項職業安全衛生設施規則第126條暨職業安全衛生法第6條第1項;機械設備器具安全標準第80條暨職業安全衛生法第6條第1項;機械設備器具安全標準第95條暨職業安全衛生法第6條第1項",
    "違反法規內容": "雇主為防止特定粉塵發生源之粉塵之發散，應依附表一乙欄所列之每一特定粉塵發生源，分別設置對應同表該欄所列設備之任何之一種或具同等以上性能之設備。;雇主對於荷重在一公噸以上之堆高機，應指派經特殊安全衛生教育、訓練人員操作。;堆高機應設置後扶架。但堆高機已註明限使用於將桅桿後傾之際貨物掉落時無引起危害之虞者，不在此限。;內圓研磨機以外之研磨輪，應設置護罩，並具有第九十六條至第一百零四條所定之性能。",
    "罰鍰金額": "",
    "備註說明": ""
}