{
    "主管機關": "桃園市",
    "公告日期": "20250509",
    "處分日期": "20250304",
    "處分字號": "114年府勞檢字第1140052342號",
    "事業單位名稱或負責人": "萬代福營造有限公司(潘國順)",
    "違法法規法條": "職業安全衛生設施規則第232條暨職業安全衛生法第6條第1項；營造安全衛生設施標準第11條之1暨職業安全衛生法第6條第1項；營造安全衛生設施標準第20條第1款暨職業安全衛生法第6條第1項；營造安全衛生設施標準第129條第3款暨職業安全衛生法第6條第1項；營造安全衛生設施標準第135條第3款暨職業安全衛生法第6條第1項",
    "違反法規內容": "雇主對於勞工有墜落危險之場所，應設置警告標示，並禁止與工作無關之人員進入。；雇主對於進入營繕工程工作場所作業人員，應提供適當安全帽，並使其正確戴用。；雇主依規定設置之護欄，應依下列規定辦理：一、具有高度九十公分以上之上欄杆、中間欄杆或等效設備（以下簡稱中欄杆）、腳趾板及杆柱等構材；其上欄杆、中欄杆及地盤面與樓板面間之上下開口距離，應不大於五十五公分。二、…。；雇主對於從事鋼筋混凝土之作業時，應依下列規定辦理：一、…。三、利用鋼筋結構作為通道時，表面應舖以木板，使能安全通行。四、…。；雇主以可調鋼管支柱為模板支撐之支柱時，應依下列規定辦理：一、…。三、可調鋼管支撐於調整高度時，應以制式之金屬附屬配件為之，不得以鋼筋等替代使用。四、…。",
    "罰鍰金額": "",
    "備註說明": ""
}