{
    "主管機關": "職業安全衛生署",
    "公告日期": "20180126",
    "處分日期": "20171017",
    "處分字號": "勞職授字第1060204445號",
    "事業單位名稱或負責人": "遠東新世紀股份有限公司",
    "違法法規法條": "職業安全衛生設施規則第21條、第29條之3、第43條第1項、第57條第1項、第58條第1項、第169條、第175條第1項、第224條第1項、第243條第1項暨職業安全衛生法第6條第1項",
    "違反法規內容": "地面積水有使勞工跌倒、滑倒之虞；廢油槽局限空間作業場所未於入口顯而易見處所公告禁止進入之規定；延伸機轉軸未設護罩、護圍等設備；對於掃除作業未採上鎖或設置標示等措施；對於自動打包機因臨時性進料作業後方鐵門開啟後忘記關閉即開始作業，造成自動化機械護圍失效；道生熱媒油管路旁堆置廢棉等可燃物未採取必要之隔離；塑膠粒吸取裝置未採取接地、使用除電劑、加濕或其他靜電消除裝置；屋頂高度2公尺以上之工作場所邊緣及開口部份，所設之女兒牆高度不足，勞工有墜落之虞；於潮濕場所使用電壓220伏特之移動式燈具未設置漏電斷路器。",
    "罰鍰金額": "",
    "備註說明": ""
}